everbug/__init__.py
everbug/middleware.py
everbug/shortcuts.py
everbug/__pycache__/__init__.cpython-35.pyc
everbug/utils/__init__.py
everbug/utils/context.py
everbug/utils/manager.py
everbug/utils/pstats.py
everbug/utils/queries.py
everbug/utils/serilalize.py
everbug-1.24.dist-info/METADATA
everbug-1.24.dist-info/RECORD
everbug-1.24.dist-info/WHEEL
everbug-1.24.dist-info/top_level.txt
